skphpprac/__init__.py
skphpprac/cli.py
skphpprac/prac1.py
skphpprac/prac10.py
skphpprac/prac11.py
skphpprac/prac12.py
skphpprac/prac13.py
skphpprac/prac14.py
skphpprac/prac15.py
skphpprac/prac16.py
skphpprac/prac17.py
skphpprac/prac18.py
skphpprac/prac19.py
skphpprac/prac2.py
skphpprac/prac20.py
skphpprac/prac21.py
skphpprac/prac22.py
skphpprac/prac23.py
skphpprac/prac24.py
skphpprac/prac25.py
skphpprac/prac26.py
skphpprac/prac3.py
skphpprac/prac4.py
skphpprac/prac5.py
skphpprac/prac6.py
skphpprac/prac7.py
skphpprac/prac8.py
skphpprac/prac9.py
skphpprac/__pycache__/__init__.cpython-312.pyc
skphpprac/__pycache__/prac1.cpython-312.pyc
skphpprac/__pycache__/prac2.cpython-312.pyc
SKPHPPRAC-2.0.0.dist-info/METADATA
SKPHPPRAC-2.0.0.dist-info/WHEEL
SKPHPPRAC-2.0.0.dist-info/top_level.txt
SKPHPPRAC-2.0.0.dist-info/RECORD
