Metadata-Version: 2.2
Name: SKPHPPRAC
Version: 2.0.0
Summary: A library of predefined PHP practicals
Author: SK
Classifier: Programming Language :: Python :: 3
Classifier: License :: OSI Approved :: MIT License
Classifier: Operating System :: OS Independent
Requires-Python: >=3.6
Dynamic: author
Dynamic: classifier
Dynamic: requires-python
Dynamic: summary
